parajax/__init__.py
parajax/py.typed
parajax-0.3.1.dist-info/WHEEL
parajax-0.3.1.dist-info/METADATA
parajax-0.3.1.dist-info/RECORD
