Metadata-Version: 2.4
Name: parajax
Version: 0.3.1
Summary: Parallelization utilities for JAX
Author: Gabriel S. Gerlero
Author-email: Gabriel S. Gerlero <ggerlero@cimec.unl.edu.ar>
License-Expression: Apache-2.0
Classifier: Development Status :: 4 - Beta
Classifier: Intended Audience :: Developers
Classifier: Programming Language :: Python
Classifier: Programming Language :: Python :: 3
Classifier: Programming Language :: Python :: 3.10
Classifier: Programming Language :: Python :: 3.11
Classifier: Programming Language :: Python :: 3.12
Classifier: Programming Language :: Python :: 3.13
Classifier: Programming Language :: Python :: 3.14
Classifier: Topic :: Software Development :: Libraries
Classifier: Typing :: Typed
Classifier: Operating System :: OS Independent
Requires-Dist: jax>=0.5,<0.9
Requires-Python: >=3.10
Project-URL: Documentation, https://parajax.readthedocs.io/
Project-URL: Homepage, https://github.com/gerlero/parajax
Project-URL: Repository, https://github.com/gerlero/parajax
